triggersms/__init__.py
triggersms/triggersms.py
triggersms-0.1.3.dist-info/METADATA
triggersms-0.1.3.dist-info/WHEEL
triggersms-0.1.3.dist-info/top_level.txt
triggersms-0.1.3.dist-info/RECORD
