Metadata-Version: 2.4
Name: triggersms
Version: 0.1.3
Summary: TriggerSMS is a Python package for sending data to the TriggerSMS API.
License: MIT
Classifier: Programming Language :: Python :: 2.6
Classifier: Programming Language :: Python :: 2.7
Classifier: Programming Language :: Python :: 3
Classifier: Operating System :: OS Independent
Requires-Python: >=2.6.6
Dynamic: classifier
Dynamic: description
Dynamic: description-content-type
Dynamic: license
Dynamic: requires-python
Dynamic: summary
